[{"userId":1,"id":1,"title":"Financial Analyst","body":"Recurrent dislocation, unspecified elbow"},
{"userId":3,"id":2,"title":"Project Manager","body":"Injury of left uterine vein, sequela"},
{"userId":4,"id":3,"title":"Statistician IV","body":"Nondisp fx of lower epiphy (separation) of l femur, sequela"},
{"userId":1,"id":4,"title":"VP Product Management","body":"Oth injuries of right shoulder and upper arm, init encntr"},
{"userId":1,"id":5,"title":"Safety Technician II","body":"Vaccines and biological substances"},
{"userId":4,"id":6,"title":"Payment Adjustment Coordinator","body":"Oth traum nondisp spondylolysis of sixth cervcal vert, 7thB"},
{"userId":4,"id":7,"title":"Developer IV","body":"Disp fx of intermed cuneiform of unsp ft, 7thG"},
{"userId":1,"id":8,"title":"Staff Accountant II","body":"Stress fracture, unsp toe(s), subs for fx w routn heal"},
{"userId":4,"id":9,"title":"Programmer Analyst II","body":"Unsp dislocation of unspecified wrist and hand, sequela"},
{"userId":3,"id":10,"title":"Social Worker","body":"Blister (nonthermal) of oral cavity, subsequent encounter"},
{"userId":3,"id":11,"title":"Analog Circuit Design manager","body":"Displ seg fx shaft of r fibula, 7thQ"},
{"userId":2,"id":12,"title":"Software Engineer II","body":"2-part nondisp fx of surgical neck of unsp humerus, sequela"},
{"userId":2,"id":13,"title":"Internal Auditor","body":"Idiopathic chronic gout, unspecified knee"},
{"userId":4,"id":14,"title":"Help Desk Technician","body":"Anterior cord syndrome at C5 level of cervical spinal cord"},
{"userId":4,"id":15,"title":"Analog Circuit Design manager","body":"Poisoning by predom beta-adrenocpt agonists, self-harm, init"},
{"userId":1,"id":16,"title":"Occupational Therapist","body":"Malignant neoplasm of accessory sinus, unspecified"},
{"userId":1,"id":17,"title":"Editor","body":"Complete loss of teeth due to other specified cause, class I"},
{"userId":4,"id":18,"title":"Help Desk Operator","body":"Other problems related to life management difficulty"},
{"userId":4,"id":19,"title":"Legal Assistant","body":"Burn of 2nd deg mul sites of right ankle and foot"},
{"userId":4,"id":20,"title":"Graphic Designer","body":"Driver of special construct vehicle injured in traf, sequela"},
{"userId":4,"id":21,"title":"Accountant IV","body":"Nondisp bicondylar fx r tibia, subs for clos fx w nonunion"},
{"userId":4,"id":22,"title":"Analog Circuit Design manager","body":"Abnlt in fetal heart rate and rhythm comp labor and delivery"},
{"userId":3,"id":23,"title":"Cost Accountant","body":"Collapsed vertebra, NEC, thoracic region, init"},
{"userId":4,"id":24,"title":"Computer Systems Analyst III","body":"Incomplete lesion of L5 level of lumbar spinal cord, sequela"},
{"userId":2,"id":25,"title":"General Manager","body":"Encounter for hearing conservation and treatment"},
{"userId":1,"id":26,"title":"Administrative Officer","body":"Traum hemor right cerebrum w/o LOC, sequela"},
{"userId":4,"id":27,"title":"Associate Professor","body":"Contracture of muscle, left ankle and foot"},
{"userId":2,"id":28,"title":"Paralegal","body":"Encounter for dental examination and cleaning"},
{"userId":2,"id":29,"title":"Operator","body":"Other injury of prostate, subsequent encounter"},
{"userId":1,"id":30,"title":"Physical Therapy Assistant","body":"Occup of 3-whl mv injured in clsn w unsp mv nontraf, subs"},
{"userId":4,"id":31,"title":"Graphic Designer","body":"Disp fx of head of left radius, subs for clos fx w nonunion"},
{"userId":1,"id":32,"title":"Nuclear Power Engineer","body":"Air embolism in childbirth"},
{"userId":4,"id":33,"title":"Geologist II","body":"Fracture of alveolus of maxilla, subs for fx w nonunion"},
{"userId":2,"id":34,"title":"Nurse","body":"Burn first deg mult sites of left lower limb, except ank/ft"},
{"userId":2,"id":35,"title":"Desktop Support Technician","body":"Displ seg fx shaft of ulna, unsp arm, 7thP"},
{"userId":3,"id":36,"title":"Web Designer III","body":"Stenosis of other vascular prosth dev/grft, sequela"},
{"userId":4,"id":37,"title":"Financial Advisor","body":"Prem separtn of placenta w oth coag defect, second trimester"},
{"userId":1,"id":38,"title":"Occupational Therapist","body":"Frostbite with tissue necrosis of unspecified sites"},
{"userId":3,"id":39,"title":"Office Assistant III","body":"Primary blast injury of lung, unilateral"},
{"userId":2,"id":40,"title":"Nurse","body":"Horseshoe tear of retina without detachment, unspecified eye"},
{"userId":4,"id":41,"title":"Research Assistant III","body":"Disp fx of dist phalanx of left less toe(s), init for opn fx"},
{"userId":3,"id":42,"title":"Help Desk Operator","body":"Drown due to oth accident to unsp watercraft"},
{"userId":1,"id":43,"title":"Health Coach IV","body":"Benign neoplasm of aortic body and other paraganglia"},
{"userId":1,"id":44,"title":"Account Coordinator","body":"Trigger finger, left index finger"},
{"userId":4,"id":45,"title":"Registered Nurse","body":"Unsp intracranial injury w LOC of unsp duration, init"},
{"userId":3,"id":46,"title":"Help Desk Operator","body":"Activity, other involving water and watercraft"},
{"userId":1,"id":47,"title":"Nurse Practicioner","body":"Corrosion of first degree of neck"},
{"userId":3,"id":48,"title":"Business Systems Development Analyst","body":"Intervertebral disc stenosis of neural canal of low extrm"},
{"userId":1,"id":49,"title":"Quality Engineer","body":"Stromal corneal pigmentations, bilateral"},
{"userId":1,"id":50,"title":"Tax Accountant","body":"Toxic effect of unsp organic solvent, undetermined, sequela"}]
